AUTHORS.rst
CHANGELOG.rst
CODE_OF_CONDUCT.rst
CONTRIBUTING.rst
LICENSE
MANIFEST.in
README.rst
dev-requirements.txt
requirements.txt
setup.cfg
setup.py
outlyer/__init__.py
outlyer/cli/__init__.py
outlyer_cli.egg-info/PKG-INFO
outlyer_cli.egg-info/SOURCES.txt
outlyer_cli.egg-info/dependency_links.txt
outlyer_cli.egg-info/entry_points.txt
outlyer_cli.egg-info/requires.txt
outlyer_cli.egg-info/top_level.txt
tests/__init__.py